{
  "pensamentos": [
    {
      "id": "1",
      "conteudo": "que bom que voce veio",
      "autoria": "Matias",
      "modelo": "modelo1"
    },
    {
      "id": "2",
      "conteudo": "testestesteste",
      "autoria": "Micael",
      "modelo": "modelo2"
    },
    {
      "id": "1",
      "conteudo": "oteste é a parte mais suave",
      "autoria": "daniel",
      "modelo": "modelo3"
    },
    {
      "id": "0ba3",
      "conteudo": "vendo se funciona",
      "autoria": "matias",
      "modelo": "modelo3"
    },
    {
      "id": "0409",
      "conteudo": "123132",
      "autoria": "123112",
      "modelo": "modelo1"
    }
  ]
}